fusera/__init__.py
fusera/compile.py
fusera/exceptions.py
fusera-0.2.0.dist-info/METADATA
fusera-0.2.0.dist-info/WHEEL
fusera-0.2.0.dist-info/top_level.txt
fusera-0.2.0.dist-info/RECORD
