Metadata-Version: 2.4
Name: fusera
Version: 0.2.0
Summary: Submit PyTorch models for cloud compilation
Author: Fusera Team
Author-email: Fusera Team <team@fusera.dev>
License: MIT
Project-URL: Homepage, https://fusera.dev
Project-URL: Documentation, https://docs.fusera.dev
Project-URL: Source, https://github.com/fusera/fusera-sdk
Classifier: Development Status :: 3 - Alpha
Classifier: Intended Audience :: Developers
Classifier: License :: OSI Approved :: MIT License
Classifier: Operating System :: OS Independent
Classifier: Programming Language :: Python :: 3
Classifier: Programming Language :: Python :: 3.9
Classifier: Programming Language :: Python :: 3.10
Classifier: Programming Language :: Python :: 3.11
Classifier: Programming Language :: Python :: 3.12
Requires-Python: >=3.9
Requires-Dist: torch>=2.5.0
Requires-Dist: requests>=2.25.0
Provides-Extra: dev
Requires-Dist: pytest>=7.4.0; extra == "dev"
Requires-Dist: pytest-cov>=4.1.0; extra == "dev"
Requires-Dist: mypy>=1.5.0; extra == "dev"
Requires-Dist: ruff>=0.1.0; extra == "dev"
Dynamic: author
Dynamic: requires-python
